[
  {
    "full_name": "austinjones/tab-rs",
    "stargazers_count": 623,
    "open_issues_count": 63,
    "forks_count": 30
  },
  {
    "full_name": "bricks-cloud/bricks",
    "stargazers_count": 35,
    "open_issues_count": 30,
    "forks_count": 2
  },
  {
    "full_name": "fharper/warm-welcome",
    "stargazers_count": 3,
    "open_issues_count": 3,
    "forks_count": 0
  },
  {
    "full_name": "boxyhq/jackson",
    "stargazers_count": 506,
    "open_issues_count": 31,
    "forks_count": 50
  },
  {
    "full_name": "apache/incubator-devlake-helm-chart",
    "stargazers_count": 15,
    "open_issues_count": 13,
    "forks_count": 21
  },
  {
    "full_name": "astuto/astuto",
    "stargazers_count": 1439,
    "open_issues_count": 43,
    "forks_count": 103
  },
  {
    "full_name": "apache/incubator-devlake",
    "stargazers_count": 2123,
    "open_issues_count": 96,
    "forks_count": 380
  },
  {
    "full_name": "sorayuki/obs-multi-rtmp",
    "stargazers_count": 2328,
    "open_issues_count": 104,
    "forks_count": 391
  },
  {
    "full_name": "juspay/hyperswitch",
    "stargazers_count": 4369,
    "open_issues_count": 253,
    "forks_count": 308
  },
  {
    "full_name": "stepci/stepci",
    "stargazers_count": 1074,
    "open_issues_count": 35,
    "forks_count": 39
  },
  {
    "full_name": "iKenndac/Tofu",
    "stargazers_count": 431,
    "open_issues_count": 45,
    "forks_count": 65
  },
  {
    "full_name": "Linen-dev/linen.dev",
    "stargazers_count": 2575,
    "open_issues_count": 55,
    "forks_count": 124
  },
  {
    "full_name": "WasmEdge/WasmEdge",
    "stargazers_count": 6260,
    "open_issues_count": 279,
    "forks_count": 567
  },
  {
    "full_name": "amplication/amplication",
    "stargazers_count": 10926,
    "open_issues_count": 465,
    "forks_count": 1015
  },
  {
    "full_name": "keptn/keptn",
    "stargazers_count": 1771,
    "open_issues_count": 47,
    "forks_count": 251
  },
  {
    "full_name": "RocketChat/Rocket.Chat",
    "stargazers_count": 35974,
    "open_issues_count": 2916,
    "forks_count": 8703
  },
  {
    "full_name": "meshery/meshery",
    "stargazers_count": 2472,
    "open_issues_count": 270,
    "forks_count": 1044
  },
  {
    "full_name": "pingcap/tidb",
    "stargazers_count": 34379,
    "open_issues_count": 4089,
    "forks_count": 5544
  },
  {
    "full_name": "gitpod-io/gitpod",
    "stargazers_count": 11195,
    "open_issues_count": 709,
    "forks_count": 1132
  },
  {
    "full_name": "remotion-dev/github-unwrapped-2022",
    "stargazers_count": 1260,
    "open_issues_count": 0,
    "forks_count": 75
  },
  {
    "full_name": "pocketbase/pocketbase",
    "stargazers_count": 24494,
    "open_issues_count": 47,
    "forks_count": 1005
  },
  {
    "full_name": "goodrain/rainbond",
    "stargazers_count": 4128,
    "open_issues_count": 123,
    "forks_count": 721
  },
  {
    "full_name": "apache/incubator-devlake-website",
    "stargazers_count": 28,
    "open_issues_count": 13,
    "forks_count": 73
  },
  {
    "full_name": "appwrite/appwrite",
    "stargazers_count": 32153,
    "open_issues_count": 807,
    "forks_count": 2810
  },
  {
    "full_name": "taosdata/TDengine",
    "stargazers_count": 21547,
    "open_issues_count": 1076,
    "forks_count": 4692
  },
  {
    "full_name": "apache/dolphinscheduler",
    "stargazers_count": 10761,
    "open_issues_count": 1064,
    "forks_count": 4013
  },
  {
    "full_name": "istio/istio",
    "stargazers_count": 33299,
    "open_issues_count": 687,
    "forks_count": 7201
  },
  {
    "full_name": "dmitryvinn/awesome-dev-advocacy",
    "stargazers_count": 209,
    "open_issues_count": 0,
    "forks_count": 21
  },
  {
    "full_name": "devstream-io/website",
    "stargazers_count": 8,
    "open_issues_count": 3,
    "forks_count": 12
  },
  {
    "full_name": "JoshuaPoddoku/global-cfps",
    "stargazers_count": 2,
    "open_issues_count": 4,
    "forks_count": 0
  }
]