[
  {
    "full_name": "merico-dev/table",
    "stargazers_count": 23,
    "open_issues_count": 52,
    "forks_count": 6
  },
  {
    "full_name": "open-sauced/app",
    "stargazers_count": 345,
    "open_issues_count": 279,
    "forks_count": 194
  },
  {
    "full_name": "HeyPuter/puter",
    "stargazers_count": 18443,
    "open_issues_count": 109,
    "forks_count": 1114
  },
  {
    "full_name": "Codium-ai/pr-agent",
    "stargazers_count": 4241,
    "open_issues_count": 20,
    "forks_count": 344
  },
  {
    "full_name": "devchat-ai/devchat-intellij",
    "stargazers_count": 7,
    "open_issues_count": 6,
    "forks_count": 4
  },
  {
    "full_name": "mfts/papermark",
    "stargazers_count": 2284,
    "open_issues_count": 59,
    "forks_count": 264
  },
  {
    "full_name": "opendilab/LLMRiddles",
    "stargazers_count": 475,
    "open_issues_count": 3,
    "forks_count": 34
  },
  {
    "full_name": "devchat-ai/devchat-vscode",
    "stargazers_count": 65,
    "open_issues_count": 6,
    "forks_count": 9
  },
  {
    "full_name": "demberto/PyFLP",
    "stargazers_count": 111,
    "open_issues_count": 28,
    "forks_count": 12
  },
  {
    "full_name": "continuedev/continue",
    "stargazers_count": 11561,
    "open_issues_count": 258,
    "forks_count": 721
  },
  {
    "full_name": "Xeift/Metamask-Mnemonic-Brute-Force",
    "stargazers_count": 54,
    "open_issues_count": 0,
    "forks_count": 23
  },
  {
    "full_name": "devchat-ai/devchat",
    "stargazers_count": 311,
    "open_issues_count": 36,
    "forks_count": 33
  },
  {
    "full_name": "austinjones/tab-rs",
    "stargazers_count": 650,
    "open_issues_count": 64,
    "forks_count": 29
  },
  {
    "full_name": "bricks-cloud/bricks",
    "stargazers_count": 60,
    "open_issues_count": 33,
    "forks_count": 5
  },
  {
    "full_name": "fharper/warm-welcome",
    "stargazers_count": 4,
    "open_issues_count": 2,
    "forks_count": 0
  },
  {
    "full_name": "boxyhq/jackson",
    "stargazers_count": 1595,
    "open_issues_count": 38,
    "forks_count": 142
  },
  {
    "full_name": "apache/incubator-devlake-helm-chart",
    "stargazers_count": 29,
    "open_issues_count": 28,
    "forks_count": 41
  },
  {
    "full_name": "astuto/astuto",
    "stargazers_count": 1703,
    "open_issues_count": 40,
    "forks_count": 132
  },
  {
    "full_name": "apache/incubator-devlake",
    "stargazers_count": 2443,
    "open_issues_count": 119,
    "forks_count": 477
  },
  {
    "full_name": "sorayuki/obs-multi-rtmp",
    "stargazers_count": 3165,
    "open_issues_count": 120,
    "forks_count": 455
  },
  {
    "full_name": "juspay/hyperswitch",
    "stargazers_count": 10494,
    "open_issues_count": 492,
    "forks_count": 1167
  },
  {
    "full_name": "stepci/stepci",
    "stargazers_count": 1515,
    "open_issues_count": 47,
    "forks_count": 63
  },
  {
    "full_name": "iKenndac/Tofu",
    "stargazers_count": 479,
    "open_issues_count": 50,
    "forks_count": 63
  },
  {
    "full_name": "Linen-dev/linen.dev",
    "stargazers_count": 2738,
    "open_issues_count": 133,
    "forks_count": 106
  },
  {
    "full_name": "WasmEdge/WasmEdge",
    "stargazers_count": 8005,
    "open_issues_count": 285,
    "forks_count": 707
  },
  {
    "full_name": "amplication/amplication",
    "stargazers_count": 13450,
    "open_issues_count": 647,
    "forks_count": 1366
  },
  {
    "full_name": "keptn/keptn",
    "stargazers_count": 1800,
    "open_issues_count": 0,
    "forks_count": 249
  },
  {
    "full_name": "RocketChat/Rocket.Chat",
    "stargazers_count": 38991,
    "open_issues_count": 3175,
    "forks_count": 9972
  },
  {
    "full_name": "meshery/meshery",
    "stargazers_count": 4888,
    "open_issues_count": 543,
    "forks_count": 1513
  },
  {
    "full_name": "pingcap/tidb",
    "stargazers_count": 36262,
    "open_issues_count": 4562,
    "forks_count": 5718
  }
]